masktranslate/__init__.py
masktranslate/main.py
mask_translate-0.1.0.dist-info/METADATA
mask_translate-0.1.0.dist-info/WHEEL
mask_translate-0.1.0.dist-info/entry_points.txt
mask_translate-0.1.0.dist-info/top_level.txt
mask_translate-0.1.0.dist-info/RECORD
