Metadata-Version: 2.1
Name: mask-translate
Version: 0.1.0
Summary: A CLI tool that masks the characters of a website or mobile application
Home-page: https://github.com/benoapp/mask-translate
Author: Hamze Shekh Najeeb
Author-email: hamze.najeeb03@gmail.com
